quasarlib/__init__.py
quasarlib/_asn1.py
quasarlib/_asymmetric.py
quasarlib/_cipher_suites.py
quasarlib/_ecdsa.py
quasarlib/_errors.py
quasarlib/_ffi.py
quasarlib/_int.py
quasarlib/_pkcs1.py
quasarlib/_pkcs12.py
quasarlib/_pkcs5.py
quasarlib/_rand.py
quasarlib/_tls.py
quasarlib/_types.py
quasarlib/asymmetric.py
quasarlib/errors.py
quasarlib/kdf.py
quasarlib/keys.py
quasarlib/symmetric.py
quasarlib/tls.py
quasarlib/trust_list.py
quasarlib/util.py
quasarlib/utilities.py
quasarlib/version.py
quasarlib/_linux_bsd/__init__.py
quasarlib/_linux_bsd/trust_list.py
quasarlib/_mac/__init__.py
quasarlib/_mac/_common_crypto.py
quasarlib/_mac/_common_crypto_cffi.py
quasarlib/_mac/_common_crypto_ctypes.py
quasarlib/_mac/_core_foundation.py
quasarlib/_mac/_core_foundation_cffi.py
quasarlib/_mac/_core_foundation_ctypes.py
quasarlib/_mac/_security.py
quasarlib/_mac/_security_cffi.py
quasarlib/_mac/_security_ctypes.py
quasarlib/_mac/asymmetric.py
quasarlib/_mac/symmetric.py
quasarlib/_mac/tls.py
quasarlib/_mac/trust_list.py
quasarlib/_mac/util.py
quasarlib/_openssl/__init__.py
quasarlib/_openssl/_libcrypto.py
quasarlib/_openssl/_libcrypto_cffi.py
quasarlib/_openssl/_libcrypto_ctypes.py
quasarlib/_openssl/_libssl.py
quasarlib/_openssl/_libssl_cffi.py
quasarlib/_openssl/_libssl_ctypes.py
quasarlib/_openssl/asymmetric.py
quasarlib/_openssl/symmetric.py
quasarlib/_openssl/tls.py
quasarlib/_openssl/util.py
quasarlib/_win/__init__.py
quasarlib/_win/_advapi32.py
quasarlib/_win/_advapi32_cffi.py
quasarlib/_win/_advapi32_ctypes.py
quasarlib/_win/_cng.py
quasarlib/_win/_cng_cffi.py
quasarlib/_win/_cng_ctypes.py
quasarlib/_win/_crypt32.py
quasarlib/_win/_crypt32_cffi.py
quasarlib/_win/_crypt32_ctypes.py
quasarlib/_win/_decode.py
quasarlib/_win/_kernel32.py
quasarlib/_win/_kernel32_cffi.py
quasarlib/_win/_kernel32_ctypes.py
quasarlib/_win/_secur32.py
quasarlib/_win/_secur32_cffi.py
quasarlib/_win/_secur32_ctypes.py
quasarlib/_win/asymmetric.py
quasarlib/_win/symmetric.py
quasarlib/_win/tls.py
quasarlib-1.0.8.dist-info/LICENSE
quasarlib-1.0.8.dist-info/METADATA
quasarlib-1.0.8.dist-info/WHEEL
quasarlib-1.0.8.dist-info/top_level.txt
quasarlib-1.0.8.dist-info/RECORD
